<?xml version="1.0" encoding="utf-8" standalone="yes"?>
<AssembliesMetrics>
  <Assembly Assembly="Subtext.Common" NTypes="17" NAbstractTypes="4" NILInstructionInAsm="2297" AfferentCoupling="12" EfferentCoupling="25" RelationalCohesion="0.82" Instability="0.68" Abstractness="0.24" DistFrMainSeq="0.06" NormDistFrMainSeq="0.09" />
  <Assembly Assembly="Subtext.Extensibility" NTypes="25" NAbstractTypes="15" NILInstructionInAsm="639" AfferentCoupling="29" EfferentCoupling="0" RelationalCohesion="0.92" Instability="0" Abstractness="0.6" DistFrMainSeq="0.28" NormDistFrMainSeq="0.4" />
  <Assembly Assembly="Subtext.Framework" NTypes="151" NAbstractTypes="40" NILInstructionInAsm="30531" AfferentCoupling="132" EfferentCoupling="63" RelationalCohesion="2.72" Instability="0.32" Abstractness="0.26" DistFrMainSeq="0.29" NormDistFrMainSeq="0.41" />
  <Assembly Assembly="Subtext.Installation" NTypes="4" NAbstractTypes="1" NILInstructionInAsm="1079" AfferentCoupling="0" EfferentCoupling="13" RelationalCohesion="1" Instability="1" Abstractness="0.25" DistFrMainSeq="0.18" NormDistFrMainSeq="0.25" />
  <Assembly Assembly="Subtext.Providers.BlogEntryEditor.FCKeditor" NTypes="3" NAbstractTypes="0" NILInstructionInAsm="1531" AfferentCoupling="1" EfferentCoupling="11" RelationalCohesion="1" Instability="0.92" Abstractness="0" DistFrMainSeq="0.06" NormDistFrMainSeq="0.08" />
  <Assembly Assembly="Subtext.Scripting" NTypes="14" NAbstractTypes="2" NILInstructionInAsm="2204" AfferentCoupling="6" EfferentCoupling="1" RelationalCohesion="2.29" Instability="0.14" Abstractness="0.14" DistFrMainSeq="0.51" NormDistFrMainSeq="0.71" />
  <Assembly Assembly="Subtext.UnitTesting.Servers" NTypes="4" NAbstractTypes="0" NILInstructionInAsm="577" AfferentCoupling="0" EfferentCoupling="10" RelationalCohesion="1.5" Instability="1" Abstractness="0" DistFrMainSeq="0" NormDistFrMainSeq="0" />
  <Assembly Assembly="Subtext.Web" NTypes="183" NAbstractTypes="15" NILInstructionInAsm="34111" AfferentCoupling="2" EfferentCoupling="94" RelationalCohesion="2.11" Instability="0.98" Abstractness="0.08" DistFrMainSeq="0.04" NormDistFrMainSeq="0.06" />
  <Assembly Assembly="Subtext.Web.Controls" NTypes="22" NAbstractTypes="3" NILInstructionInAsm="5057" AfferentCoupling="53" EfferentCoupling="9" RelationalCohesion="0.86" Instability="0.15" Abstractness="0.14" DistFrMainSeq="0.51" NormDistFrMainSeq="0.72" />
</AssembliesMetrics>